hdfury/__init__.py
hdfury/api.py
hdfury/const.py
hdfury/exceptions.py
hdfury-1.4.2.dist-info/METADATA
hdfury-1.4.2.dist-info/WHEEL
hdfury-1.4.2.dist-info/licenses/LICENCE
hdfury-1.4.2.dist-info/RECORD
