Metadata-Version: 2.4
Name: hdfury
Version: 1.4.2
Summary: Asynchronous Python client for HDFury devices
Project-URL: Homepage, https://github.com/glenndehaan/python-hdfury
Project-URL: Issues, https://github.com/glenndehaan/python-hdfury/issues
Author-email: Glenn de Haan <glenn@dehaan.cloud>
License: MIT
License-File: LICENCE
Requires-Python: >=3.10
Requires-Dist: aiohttp>=3.0.0
